{"metadata": {"dbt_schema_version": "https://schemas.getdbt.com/dbt/run-results/v6.json", "dbt_version": "1.9.4", "generated_at": "2025-04-16T16:58:35.796484Z", "invocation_id": "8e6b6be4-0841-416b-abad-b84a2d802981", "env": {}}, "results": [{"status": "success", "timing": [{"name": "compile", "started_at": "2025-04-16T16:58:32.605385Z", "completed_at": "2025-04-16T16:58:32.617296Z"}, {"name": "execute", "started_at": "2025-04-16T16:58:32.618135Z", "completed_at": "2025-04-16T16:58:33.475052Z"}], "thread_id": "main", "execution_time": 0.869667, "adapter_response": {}, "message": "learn_dbt.on-run-start.0 passed", "failures": 0, "unique_id": "operation.learn_dbt.learn_dbt-on-run-start-0", "compiled": true, "compiled_code": "USE WAREHOUSE transform_wh;", "relation_name": null, "batch_results": null}, {"status": "success", "timing": [{"name": "compile", "started_at": "2025-04-16T16:58:33.481611Z", "completed_at": "2025-04-16T16:58:33.486189Z"}, {"name": "execute", "started_at": "2025-04-16T16:58:33.486961Z", "completed_at": "2025-04-16T16:58:35.126636Z"}], "thread_id": "Thread-1 (worker)", "execution_time": 1.6458020210266113, "adapter_response": {"_message": "SUCCESS 1", "code": "SUCCESS", "rows_affected": 1, "query_id": "01bbbb3a-0002-af26-0007-cb6200031026"}, "message": "SUCCESS 1", "failures": null, "unique_id": "model.learn_dbt.my_first_model", "compiled": true, "compiled_code": "\n\nselect\n    1 as id,\n    'first record' as description", "relation_name": "analytics.dbt.my_first_model", "batch_results": null}, {"status": "success", "timing": [{"name": "compile", "started_at": "2025-04-16T16:58:35.129631Z", "completed_at": "2025-04-16T16:58:35.131551Z"}, {"name": "execute", "started_at": "2025-04-16T16:58:35.131697Z", "completed_at": "2025-04-16T16:58:35.529221Z"}], "thread_id": "Thread-1 (worker)", "execution_time": 0.4001131057739258, "adapter_response": {"_message": "SUCCESS 1", "code": "SUCCESS", "rows_affected": 1, "query_id": "01bbbb3a-0002-af26-0007-cb620003102a"}, "message": "SUCCESS 1", "failures": null, "unique_id": "model.learn_dbt.my_second_model", "compiled": true, "compiled_code": "\n\nselect\n    id,\n    description,\n    'processed' as status\nfrom analytics.dbt.my_first_model", "relation_name": "analytics.dbt.my_second_model", "batch_results": null}], "elapsed_time": 4.192782163619995, "args": {"require_batched_execution_for_custom_microbatch_strategy": false, "log_file_max_bytes": 10485760, "printer_width": 80, "exclude": [], "defer": false, "populate_cache": true, "skip_nodes_if_on_run_start_fails": false, "send_anonymous_usage_stats": true, "write_json": true, "require_resource_names_without_spaces": false, "indirect_selection": "eager", "use_colors_file": true, "show_resource_report": false, "cache_selected_only": false, "favor_state": false, "log_format_file": "debug", "partial_parse": true, "static_parser": true, "warn_error_options": {"include": [], "exclude": []}, "vars": {}, "state_modified_compare_more_unrendered_values": false, "state_modified_compare_vars": false, "use_colors": true, "macro_debugging": false, "require_yaml_configuration_for_mf_time_spines": false, "log_level_file": "debug", "invocation_command": "dbt run", "require_nested_cumulative_type_params": false, "log_path": "/Users/neil.lewis/Desktop/dbt_snowflake_learning/learn-dbt/logs", "project_dir": "/Users/neil.lewis/Desktop/dbt_snowflake_learning/learn-dbt", "strict_mode": false, "empty": false, "select": [], "log_format": "default", "partial_parse_file_diff": true, "profiles_dir": "/Users/neil.lewis/.dbt", "which": "run", "print": true, "quiet": false, "require_explicit_package_overrides_for_builtin_materializations": true, "log_level": "info", "version_check": true, "introspect": true, "source_freshness_run_project_hooks": false}}